odoo9_addon_res_config_settings_enterprise_remove-9.0.1.0.0.99.dev4-py2.7-nspkg.pth
odoo9_addon_res_config_settings_enterprise_remove-9.0.1.0.0.99.dev4.dist-info/DESCRIPTION.rst
odoo9_addon_res_config_settings_enterprise_remove-9.0.1.0.0.99.dev4.dist-info/METADATA
odoo9_addon_res_config_settings_enterprise_remove-9.0.1.0.0.99.dev4.dist-info/RECORD
odoo9_addon_res_config_settings_enterprise_remove-9.0.1.0.0.99.dev4.dist-info/WHEEL
odoo9_addon_res_config_settings_enterprise_remove-9.0.1.0.0.99.dev4.dist-info/metadata.json
odoo9_addon_res_config_settings_enterprise_remove-9.0.1.0.0.99.dev4.dist-info/namespace_packages.txt
odoo9_addon_res_config_settings_enterprise_remove-9.0.1.0.0.99.dev4.dist-info/top_level.txt
odoo_addons/res_config_settings_enterprise_remove/README.rst
odoo_addons/res_config_settings_enterprise_remove/__init__.py
odoo_addons/res_config_settings_enterprise_remove/__openerp__.py
odoo_addons/res_config_settings_enterprise_remove/i18n/res_config_settings_enterprise_remove.pot
odoo_addons/res_config_settings_enterprise_remove/models/__init__.py
odoo_addons/res_config_settings_enterprise_remove/models/res_config_settings.py
odoo_addons/res_config_settings_enterprise_remove/static/description/icon.png
