Metadata-Version: 2.0
Name: odoo9-addon-res-config-settings-enterprise-remove
Version: 9.0.1.0.0.99.dev4
Summary: Remove fields in all settings views marked as enterprise
Home-page: https://laslabs.com
Author: LasLabs, Odoo Community Association (OCA)
Author-email: support@odoo-community.org
License: AGPL-3
Platform: UNKNOWN
Classifier: Programming Language :: Python
Classifier: Framework :: Odoo
Classifier: License :: OSI Approved :: GNU Affero General Public License v3
Requires-Python: ~=2.7
Requires-Dist: odoo (<9.1a,>=9.0a)
